ika/__init__.py
ika/driver.py
ika/mock.py
ika/util.py
ika_control-0.6.1.dist-info/LICENSE
ika_control-0.6.1.dist-info/METADATA
ika_control-0.6.1.dist-info/WHEEL
ika_control-0.6.1.dist-info/entry_points.txt
ika_control-0.6.1.dist-info/top_level.txt
ika_control-0.6.1.dist-info/RECORD
