Metadata-Version: 2.1
Name: ika-control
Version: 0.6.1
Summary: Python driver for IKA instruments.
Home-page: https://github.com/numat/ika/
Author: Alex Ruddick
Author-email: a.ruddick@numat-tech.com
License: GPLv3
Classifier: License :: OSI Approved :: GNU General Public License v3 (GPLv3)
Classifier: Development Status :: 4 - Beta
Classifier: Natural Language :: English
Classifier: Programming Language :: Python
Classifier: Programming Language :: Python :: 3
Classifier: Programming Language :: Python :: 3.8
Classifier: Programming Language :: Python :: 3.9
Classifier: Programming Language :: Python :: 3.10
Classifier: Programming Language :: Python :: 3.11
Classifier: Programming Language :: Python :: 3.12
Classifier: Topic :: Scientific/Engineering :: Human Machine Interfaces
License-File: LICENSE
Requires-Dist: pyserial
Provides-Extra: test
Requires-Dist: pytest <8,>=6 ; extra == 'test'
Requires-Dist: pytest-cov <6,>=5 ; extra == 'test'
Requires-Dist: pytest-asyncio ==0.* ; extra == 'test'
Requires-Dist: pytest-xdist ==3.* ; extra == 'test'
Requires-Dist: ruff ==0.4.7 ; extra == 'test'
Requires-Dist: mypy ==1.10.1 ; extra == 'test'
Requires-Dist: types-pyserial ==3.5.0.20240311 ; extra == 'test'
